{
    "5874348944": {
        "plan": "ğ—©ğ—œğ—£",
        "timer": "2030-12-30 00:00"
    },
    "7538420552": {
        "plan": "ğ—™ğ—¥ğ—˜ğ—˜",
        "timer": "none"
    },
    "7371519921": {
        "plan": "ğ—™ğ—¥ğ—˜ğ—˜",
        "timer": "none"
    },
    "5817828281": {
        "plan": "VIP",
        "timer": "2024-12-15 06:38",
        "paln": "FREE"
    },
    "6965078723": {
        "plan": "FREE",
        "timer": "none"
    },
    "SAOUD-SFHQ-561H-JQC3": {
        "plan": "VIP",
        "time": "2024-11-03 06:32"
    },
    "SUFI-1OJZ-D1NW-0H33": {
        "plan": "VIP",
        "time": "2024-11-03 06:43"
    },
    "7433445671": {
        "plan": "VIP",
        "timer": "none",
        "paln": "FREE"
    },
    "SUFI-60X0-2IJ4-I7O9": {
        "plan": "VIP",
        "time": "2024-11-03 15:57"
    },
    "6370870810": {
        "plan": "FREE",
        "timer": "none"
    },
    "5533074654": {
        "plan": "FREE",
        "timer": "none"
    },
    "6627893716": {
        "plan": "FREE",
        "timer": "none"
    },
    "6332270659": {
        "plan": "FREE",
        "timer": "none"
    }
}